flask_express/__init__.py
flask_express/_helper.py
flask_express/munch.py
flask_express/request.py
flask_express/response.py
flask_express/typing.py
Flask_Express-0.1.4.dist-info/LICENSE
Flask_Express-0.1.4.dist-info/METADATA
Flask_Express-0.1.4.dist-info/WHEEL
Flask_Express-0.1.4.dist-info/top_level.txt
Flask_Express-0.1.4.dist-info/RECORD
